LICENSE
setup.py
oeel/EE_node_server.js
oeel/__init__.py
oeel/external.py
oeel/oeel.py
oeel.egg-info/PKG-INFO
oeel.egg-info/SOURCES.txt
oeel.egg-info/dependency_links.txt
oeel.egg-info/requires.txt
oeel.egg-info/top_level.txt